{
  "main": {
    "id": "9631d862d631408a",
    "type": "split",
    "children": [
      {
        "id": "b6cbf299baf75baf",
        "type": "tabs",
        "children": [
          {
            "id": "21e33ffe9185e783",
            "type": "leaf",
            "state": {
              "type": "markdown",
              "state": {
                "file": "Projects.md",
                "mode": "source",
                "source": false
              },
              "icon": "lucide-file",
              "title": "Projects"
            }
          }
        ]
      }
    ],
    "direction": "vertical"
  },
  "left": {
    "id": "bc706ba5d81b3ecc",
    "type": "split",
    "children": [
      {
        "id": "54cf4d52c4321a7e",
        "type": "tabs",
        "children": [
          {
            "id": "0584b03ca849a1b7",
            "type": "leaf",
            "state": {
              "type": "file-explorer",
              "state": {
                "sortOrder": "alphabetical",
                "autoReveal": false
              },
              "icon": "lucide-folder-closed",
              "title": "Files"
            }
          },
          {
            "id": "a1180052a7246926",
            "type": "leaf",
            "state": {
              "type": "search",
              "state": {
                "query": "",
                "matchingCase": false,
                "explainSearch": false,
                "collapseAll": false,
                "extraContext": false,
                "sortOrder": "alphabetical"
              },
              "icon": "lucide-search",
              "title": "Search"
            }
          },
          {
            "id": "265577ba214ec916",
            "type": "leaf",
            "state": {
              "type": "bookmarks",
              "state": {},
              "icon": "lucide-bookmark",
              "title": "Bookmarks"
            }
          }
        ]
      }
    ],
    "direction": "horizontal",
    "width": 378.5
  },
  "right": {
    "id": "4f9b0fe2abd2fde5",
    "type": "split",
    "children": [
      {
        "id": "e16628fcf58a8c0d",
        "type": "tabs",
        "children": [
          {
            "id": "425713be9df43294",
            "type": "leaf",
            "state": {
              "type": "backlink",
              "state": {
                "file": "DBMS.md",
                "collapseAll": false,
                "extraContext": false,
                "sortOrder": "alphabetical",
                "showSearch": false,
                "searchQuery": "",
                "backlinkCollapsed": false,
                "unlinkedCollapsed": true
              },
              "icon": "links-coming-in",
              "title": "Backlinks for DBMS"
            }
          },
          {
            "id": "666ea7f6f856c264",
            "type": "leaf",
            "state": {
              "type": "outgoing-link",
              "state": {
                "file": "DBMS.md",
                "linksCollapsed": false,
                "unlinkedCollapsed": true
              },
              "icon": "links-going-out",
              "title": "Outgoing links from DBMS"
            }
          },
          {
            "id": "6961a6cde3acddf4",
            "type": "leaf",
            "state": {
              "type": "tag",
              "state": {
                "sortOrder": "frequency",
                "useHierarchy": true,
                "showSearch": false,
                "searchQuery": ""
              },
              "icon": "lucide-tags",
              "title": "Tags"
            }
          },
          {
            "id": "6f9887664bd361ff",
            "type": "leaf",
            "state": {
              "type": "outline",
              "state": {
                "file": "DBMS.md",
                "followCursor": false,
                "showSearch": false,
                "searchQuery": ""
              },
              "icon": "lucide-list",
              "title": "Outline of DBMS"
            }
          }
        ]
      }
    ],
    "direction": "horizontal",
    "width": 300,
    "collapsed": true
  },
  "left-ribbon": {
    "hiddenItems": {
      "bases:Create new base": false,
      "switcher:Open quick switcher": false,
      "graph:Open graph view": false,
      "canvas:Create new canvas": false,
      "daily-notes:Open today's daily note": false,
      "templates:Insert template": false,
      "command-palette:Open command palette": false
    }
  },
  "active": "21e33ffe9185e783",
  "lastOpenFiles": [
    "Pratik Tata.md",
    "Projects.md",
    "API.md",
    "DBMS.md",
    "Git.md",
    "Maven.md",
    "Spring Boot Annotations Full Signature.md",
    "System Design.md",
    "Untitled.canvas",
    "Untitled 2.base",
    "Untitled 1.base",
    "Architecture Java, Maven.md",
    "Multi-threading and concurrency.md",
    "Kafka.md",
    "Spring Security.md",
    "Time complexity Cheat Sheet.md",
    "Untitled.base",
    "Design Patterns.md",
    "Misc.md",
    "DSA.md",
    "Hibernate.md",
    "Interview Prep.md",
    "Pasted image 20250927232551.png",
    "Java 8 to 21.md",
    "Master Guide to Software Design Diagrams.md",
    "Untitled 1.md",
    "Welcome.md"
  ]
}